pqcomponents/PQBarcode.py
pqcomponents/PQBluetooth.py
pqcomponents/PQBluetoothClient.py
pqcomponents/PQBluetoothServer.py
pqcomponents/PQBluetoothctl.py
pqcomponents/PQEthernet.py
pqcomponents/PQGPIO.py
pqcomponents/PQPWM.py
pqcomponents/PQSerial.py
pqcomponents/PQSound.py
pqcomponents/PQTcpClient.py
pqcomponents/PQTcpServer.py
pqcomponents/PQWifi.py
pqcomponents/__init__.py
pqcomponents-1.0.14.dist-info/METADATA
pqcomponents-1.0.14.dist-info/WHEEL
pqcomponents-1.0.14.dist-info/top_level.txt
pqcomponents-1.0.14.dist-info/RECORD
