Metadata-Version: 2.1
Name: pqcomponents
Version: 1.0.14
Summary: A custom PyQt5 widgets package
Home-page: https://github.com/JunKyu-Cho/pqcomponents
Author: JunKyu
Author-email: jkjo0619@gmail.com
License: UNKNOWN
Platform: UNKNOWN
Classifier: Programming Language :: Python :: 3
Classifier: License :: OSI Approved :: MIT License
Classifier: Operating System :: OS Independent
Requires-Python: >=3.6
Requires-Dist: PyQt5>=5.15.0
Requires-Dist: pexpect>=4.8.0
Requires-Dist: psutil>=5.8.0
Requires-Dist: wifi>=0.3.8
Requires-Dist: pyserial>=3.3
